nws_api_client/__init__.py
nws_api_client/_hooks/__init__.py
nws_api_client/_hooks/registration.py
nws_api_client/_hooks/sdkhooks.py
nws_api_client/_hooks/types.py
nws_api_client/_version.py
nws_api_client/alerts.py
nws_api_client/aviation.py
nws_api_client/basesdk.py
nws_api_client/conditions.py
nws_api_client/forecasts.py
nws_api_client/geographic.py
nws_api_client/httpclient.py
nws_api_client/metadata.py
nws_api_client/models/__init__.py
nws_api_client/models/components/__init__.py
nws_api_client/models/components/alert.py
nws_api_client/models/components/alertcertainty.py
nws_api_client/models/components/alertcollectiongeojson.py
nws_api_client/models/components/alertcollectionjsonld.py
nws_api_client/models/components/alertgeojson.py
nws_api_client/models/components/alertjsonld.py
nws_api_client/models/components/alertmessagetype.py
nws_api_client/models/components/alertmessagetype_parameter.py
nws_api_client/models/components/alertregiontype.py
nws_api_client/models/components/alertsactivecount.py
nws_api_client/models/components/alertseverity.py
nws_api_client/models/components/alertstatus.py
nws_api_client/models/components/alertstatus_parameter.py
nws_api_client/models/components/alertstypes.py
nws_api_client/models/components/alerturgency.py
nws_api_client/models/components/areacode.py
nws_api_client/models/components/centerweatheradvisory.py
nws_api_client/models/components/centerweatheradvisorycollectiongeojson.py
nws_api_client/models/components/centerweatheradvisorygeojson.py
nws_api_client/models/components/centerweatherserviceunitjsonld.py
nws_api_client/models/components/geojsongeometry.py
nws_api_client/models/components/glossary.py
nws_api_client/models/components/glossaryterm.py
nws_api_client/models/components/gridpoint.py
nws_api_client/models/components/gridpointforecast.py
nws_api_client/models/components/gridpointforecastfeatureflags.py
nws_api_client/models/components/gridpointforecastgeojson.py
nws_api_client-0.13.1.dist-info/LICENSE
nws_api_client-0.13.1.dist-info/METADATA
nws_api_client-0.13.1.dist-info/WHEEL
nws_api_client-0.13.1.dist-info/RECORD
