Metadata-Version: 2.3
Name: nws-api-client
Version: 0.13.1
Summary: OpenAPI Client SDK for National Weather Service API (NWS / weather.gov)
Author: Dustin Miller
Requires-Python: >=3.9
Classifier: Programming Language :: Python :: 3
Classifier: Programming Language :: Python :: 3.9
Classifier: Programming Language :: Python :: 3.10
Classifier: Programming Language :: Python :: 3.11
Classifier: Programming Language :: Python :: 3.12
Classifier: Programming Language :: Python :: 3.13
Requires-Dist: httpx (>=0.28.1)
Requires-Dist: pydantic (>=2.11.2)
Project-URL: Documentation, https://github.com/spdustin/nws-api-client-python
Project-URL: Homepage, https://github.com/spdustin/nws-api-client-python
Project-URL: Repository, https://github.com/spdustin/nws-api-client-python.git
